mcp_runcmd_server/__init__.py
mcp_runcmd_server/main.py
mcp_runcmd_server-2.0.dist-info/licenses/LICENSE
mcp_runcmd_server-2.0.dist-info/METADATA
mcp_runcmd_server-2.0.dist-info/WHEEL
mcp_runcmd_server-2.0.dist-info/entry_points.txt
mcp_runcmd_server-2.0.dist-info/top_level.txt
mcp_runcmd_server-2.0.dist-info/RECORD
