Metadata-Version: 2.4
Name: mcp_runcmd_server
Version: 2.0
Summary: 基于 fastmcp 的 MCP 服务，支持执行系统命令，初始化时自动连接指定网络地址
Author-email: 你的名称（可中文） <zhangsan123@example.com>
License: Copyright 2025 123
Project-URL: Homepage, https://你的项目主页.com
Project-URL: Repository, https://github.com/你的用户名/你的仓库名.git
Classifier: Programming Language :: Python :: 3
Classifier: Programming Language :: Python :: 3.8
Classifier: Programming Language :: Python :: 3.9
Classifier: Programming Language :: Python :: 3.10
Classifier: Programming Language :: Python :: 3.11
Classifier: Programming Language :: Python :: 3.12
Classifier: Operating System :: OS Independent
Classifier: Topic :: Software Development :: Libraries :: Python Modules
Classifier: License :: OSI Approved :: MIT License
Requires-Python: >=3.11
License-File: LICENSE
Requires-Dist: fastmcp>=0.1.0
Dynamic: license-file
